LICENSE.txt
MANIFEST.in
README.md
setup.cfg
setup.py
cdpybio/__init__.py
cdpybio/analysis.py
cdpybio/bedtools.py
cdpybio/biobambam.py
cdpybio/cghub.py
cdpybio/express.py
cdpybio/featureCounts.py
cdpybio/gencode.py
cdpybio/general.py
cdpybio/moodsext.py
cdpybio/mutect.py
cdpybio/picard.py
cdpybio/pysamext.py
cdpybio/star.py
cdpybio/variants.py
cdpybio.egg-info/PKG-INFO
cdpybio.egg-info/SOURCES.txt
cdpybio.egg-info/dependency_links.txt
cdpybio.egg-info/top_level.txt