Metadata-Version: 1.1
Name: cdpybio
Version: 0.0.7
Summary: A collection of useful methods for working with various bioinformatics data, software output files, etc.
Home-page: https://github.com/cdeboever3/cdpybio
Author: Christopher DeBoever
Author-email: cdeboever3@gmail.com
License: MIT
Download-URL: https://github.com/cdeboever3/cdpybio/tarball/0.0.7
Keywords: bioinformatics
Platform: UNKNOWN
Classifier: Development Status :: 2 - Pre-Alpha
Classifier: Intended Audience :: Science/Research
Classifier: License :: OSI Approved :: MIT License
Classifier: Natural Language :: English
Classifier: Topic :: Scientific/Engineering :: Bio-Informatics
